eaves/__init__.py
eaves/eaves.py
eaves_python-0.1.9.dist-info/METADATA
eaves_python-0.1.9.dist-info/WHEEL
eaves_python-0.1.9.dist-info/top_level.txt
eaves_python-0.1.9.dist-info/RECORD
