Metadata-Version: 2.1
Name: eaves-python
Version: 0.1.9
Summary: Wrapper around pygame cause why NOT
Home-page: https://github.com/coverosu/eaves
Author: coverosu
Author-email: coverosu@gmail.com
License: UNKNOWN
Platform: UNKNOWN
Classifier: Programming Language :: Python :: 3
Classifier: License :: OSI Approved :: MIT License
Classifier: Operating System :: OS Independent
Requires-Python: >=3.9
